LICENCE.txt
MANIFEST.in
README.md
README_PYPI.rst
setup.cfg
setup.py
Alfred_PyWorkflow.egg-info/PKG-INFO
Alfred_PyWorkflow.egg-info/SOURCES.txt
Alfred_PyWorkflow.egg-info/dependency_links.txt
Alfred_PyWorkflow.egg-info/not-zip-safe
Alfred_PyWorkflow.egg-info/top_level.txt
tests/test_background.py
tests/test_notify.py
tests/test_update.py
tests/test_update_versions.py
tests/test_util.py
tests/test_util_atomic.py
tests/test_util_lockfile.py
tests/test_util_uninterruptible.py
tests/test_web.py
tests/test_web_http_encoding.py
tests/test_workflow.py
tests/test_workflow_encoding.py
tests/test_workflow_env.py
tests/test_workflow_files.py
tests/test_workflow_filter.py
tests/test_workflow_import.py
tests/test_workflow_json.py
tests/test_workflow_keychain.py
tests/test_workflow_magic.py
tests/test_workflow_run.py
tests/test_workflow_serializers.py
tests/test_workflow_settings.py
tests/test_workflow_update.py
tests/test_workflow_versions.py
workflow/__init__.py
workflow/background.py
workflow/notify.py
workflow/update.py
workflow/util.py
workflow/version
workflow/web.py
workflow/workflow.py