Metadata-Version: 2.2
Name: Alfred-PyWorkflow
Version: 2.1.0
Summary: Full-featured helper library for writing Alfred 4 and 5 workflows
Home-page: https://xdevcloud.de/alfred-pyworkflow/
Author: Thomas Harr
Author-email: xDevThomas@gmail.com
Keywords: alfred workflow alfred4 alfred5
Classifier: Development Status :: 5 - Production/Stable
Classifier: License :: OSI Approved :: MIT License
Classifier: Operating System :: MacOS :: MacOS X
Classifier: Intended Audience :: Developers
Classifier: Natural Language :: English
Classifier: Programming Language :: Python :: 3.9
Classifier: Programming Language :: Python :: 3.10
Classifier: Programming Language :: Python :: 3.11
Classifier: Programming Language :: Python :: 3.12
Classifier: Programming Language :: Python :: 3.13
Classifier: Programming Language :: Python :: 3.14
Classifier: Topic :: Software Development :: Libraries
Classifier: Topic :: Software Development :: Libraries :: Application Frameworks
License-File: LICENCE.txt
Dynamic: author
Dynamic: author-email
Dynamic: classifier
Dynamic: description
Dynamic: home-page
Dynamic: keywords
Dynamic: summary
